dhyolo/__init__.py
dhyolo/detect.py
dhyolo/export.py
dhyolo/hubconf.py
dhyolo/model.py
dhyolo/models/__init__.py
dhyolo/models/common.py
dhyolo/models/experimental.py
dhyolo/models/tf.py
dhyolo/models/yolo.py
dhyolo/utils/__init__.py
dhyolo/utils/activations.py
dhyolo/utils/augmentations.py
dhyolo/utils/autoanchor.py
dhyolo/utils/autobatch.py
dhyolo/utils/callbacks.py
dhyolo/utils/dataloaders.py
dhyolo/utils/downloads.py
dhyolo/utils/general.py
dhyolo/utils/loss.py
dhyolo/utils/metrics.py
dhyolo/utils/plots.py
dhyolo/utils/torch_utils.py
dhyolo/utils/triton.py
dhyolo/utils/aws/__init__.py
dhyolo/utils/aws/resume.py
dhyolo/utils/loggers/__init__.py
dhyolo/utils/loggers/clearml/__init__.py
dhyolo/utils/loggers/clearml/clearml_utils.py
dhyolo/utils/loggers/clearml/hpo.py
dhyolo/utils/loggers/comet/__init__.py
dhyolo/utils/loggers/comet/comet_utils.py
dhyolo/utils/loggers/comet/hpo.py
dhyolo/utils/loggers/wandb/__init__.py
dhyolo/utils/loggers/wandb/wandb_utils.py
dhyolo/utils/segment/__init__.py
dhyolo/utils/segment/augmentations.py
dhyolo/utils/segment/dataloaders.py
dhyolo/utils/segment/general.py
dhyolo/utils/segment/loss.py
dhyolo/utils/segment/metrics.py
dhyolo/utils/segment/plots.py
iteach_dhyolo-0.3.dist-info/METADATA
iteach_dhyolo-0.3.dist-info/WHEEL
iteach_dhyolo-0.3.dist-info/top_level.txt
iteach_dhyolo-0.3.dist-info/RECORD
