Metadata-Version: 2.1
Name: iteach_dhyolo
Version: 0.3
Summary: The iteach package includes the dhyolo model, designed to detect doors and handles in images.
Home-page: https://irvlutd.github.io/iTeach
Author: Vinaya Bomnale
Author-email: vinaya.bomnale@utdallas.edu
Requires-Dist: gitpython >=3.1.30
Requires-Dist: matplotlib >=3.3
Requires-Dist: numpy >=1.22.2
Requires-Dist: opencv-python >=4.1.1
Requires-Dist: Pillow >=7.1.2
Requires-Dist: psutil
Requires-Dist: PyYAML >=5.3.1
Requires-Dist: requests >=2.23.0
Requires-Dist: scipy >=1.4.1
Requires-Dist: thop >=0.1.1
Requires-Dist: torch >=1.8.0
Requires-Dist: torchvision >=0.9.0
Requires-Dist: tqdm >=4.64.0
Requires-Dist: ultralytics >=8.0.147
Requires-Dist: pandas >=1.1.4
Requires-Dist: seaborn >=0.11.0
Requires-Dist: setuptools >=65.5.1
Requires-Dist: easydict
Requires-Dist: huggingface-hub
